r2c/__init__.py
r2c/lib/__init__.py
r2c/lib/analysis/__init__.py
r2c/lib/analysis/dependency_mounter.py
r2c/lib/analysis/execution_order.py
r2c/lib/analysis/mount_manager.py
r2c/lib/analysis/output_storage.py
r2c/lib/analyzer.py
r2c/lib/constants.py
r2c/lib/errors.py
r2c/lib/filestore.py
r2c/lib/input.py
r2c/lib/jobdef.py
r2c/lib/manifest.py
r2c/lib/manifest_migrations.py
r2c/lib/py.typed
r2c/lib/registry.py
r2c/lib/schemas/__init__.py
r2c/lib/schemas/analyzer_output.0.1.0.json
r2c/lib/schemas/analyzer_output.1.0.0.json
r2c/lib/schemas/integration_test.1.0.0.json
r2c/lib/schemas/integration_test.2.0.0.json
r2c/lib/schemas/json-schema.draft-07.json
r2c/lib/schemas/manifest.1.0.0.json
r2c/lib/schemas/manifest.1.1.0.json
r2c/lib/schemas/manifest.1.2.0.json
r2c/lib/schemas/manifest.2.0.0.json
r2c/lib/schemas/manifest.2.1.0.json
r2c/lib/schemas/test_logic.py
r2c/lib/specified_analyzer.py
r2c/lib/util.py
r2c/lib/versioned_analyzer.py
r2c_lib-0.0.18.dist-info/WHEEL
r2c_lib-0.0.18.dist-info/METADATA
r2c_lib-0.0.18.dist-info/RECORD
