Metadata-Version: 2.1
Name: r2c-lib
Version: 0.0.18
Summary: Supporting libraries for R2C
Home-page: https://ret2.co
Author: R2C
Author-email: cli@ret2.co
Requires-Python: >=3.6,<4.0
Classifier: License :: Other/Proprietary License
Classifier: Operating System :: OS Independent
Classifier: Programming Language :: Python :: 3
Classifier: Programming Language :: Python :: 3.6
Classifier: Programming Language :: Python :: 3.7
Requires-Dist: cattrs (>=0.9.0,<0.10.0)
Requires-Dist: docker (>=3.7,<4.0)
Requires-Dist: gitpython (>=2.1,<3.0)
Requires-Dist: importlib_resources (>=1.0,<2.0)
Requires-Dist: jsondiff (>=1.1,<2.0)
Requires-Dist: jsonschema (>=3.0,<4.0)
Requires-Dist: mypy-extensions (>=0.4,<0.5)
Requires-Dist: requests (>=2.0,<3.0)
Requires-Dist: semantic-version (>=2.7,<3.0)
Requires-Dist: toposort (>=1.5,<2.0)
